README.md
setup.py
SaranyaSumThree/SumThree.py
SaranyaSumThree/__init__.py
SaranyaSumThree.egg-info/PKG-INFO
SaranyaSumThree.egg-info/SOURCES.txt
SaranyaSumThree.egg-info/dependency_links.txt
SaranyaSumThree.egg-info/top_level.txt