Metadata-Version: 2.1
Name: SaranyaSumThree
Version: 1.0.0
Summary: It Outputs sum of three numbers
Home-page: https://github.com/saranya-sekar/SaranyaSumThree
Author: Saranya Sekar
Author-email: saranyatagore@yahoo.com
License: MIT
Download-URL: https://github.com/saranya-sekar/SaranyaSumThree/archive/refs/tags/final-01.tar.gz
Platform: UNKNOWN
Classifier: License :: OSI Approved :: MIT License
Classifier: Programming Language :: Python :: 3.6
Classifier: Programming Language :: Python :: 3.7
Classifier: Programming Language :: Python :: 3.8
